uniir_for_pyserini/common/config_updater.py
uniir_for_pyserini/common/dist_utils.py
uniir_for_pyserini/common/interactive_retriever.py
uniir_for_pyserini/common/mbeir_analyst.py
uniir_for_pyserini/common/mbeir_embedder.py
uniir_for_pyserini/common/mbeir_retriever.py
uniir_for_pyserini/common/utils.py
uniir_for_pyserini/data/__init__.py
uniir_for_pyserini/data/mbeir_data_generator.py
uniir_for_pyserini/data/mbeir_data_utils.py
uniir_for_pyserini/data/mbeir_dataset.py
uniir_for_pyserini/data/preprocessing/__init__.py
uniir_for_pyserini/data/preprocessing/cirr_data_preprocessor.py
uniir_for_pyserini/data/preprocessing/edis_data_preprocessor.py
uniir_for_pyserini/data/preprocessing/fashion200k_data_preprocessor.py
uniir_for_pyserini/data/preprocessing/fashioniq_data_preprocessor.py
uniir_for_pyserini/data/preprocessing/infoseek_data_preprocessor.py
uniir_for_pyserini/data/preprocessing/mscoco_data_preprocessor.py
uniir_for_pyserini/data/preprocessing/nights_data_preprocessor.py
uniir_for_pyserini/data/preprocessing/oven_data_preprocessor.py
uniir_for_pyserini/data/preprocessing/utils.py
uniir_for_pyserini/data/preprocessing/visualnews_data_preprocessor.py
uniir_for_pyserini/data/preprocessing/webqa_data_preprocessor.py
uniir_for_pyserini/models/__init__.py
uniir_for_pyserini/models/uniir_blip/__init__.py
uniir_for_pyserini/models/uniir_blip/engine.py
uniir_for_pyserini/models/uniir_blip/train.py
uniir_for_pyserini/models/uniir_blip/utils.py
uniir_for_pyserini/models/uniir_blip/backbone/__init__.py
uniir_for_pyserini/models/uniir_blip/backbone/blip.py
uniir_for_pyserini/models/uniir_blip/backbone/med.py
uniir_for_pyserini/models/uniir_blip/backbone/vit.py
uniir_for_pyserini/models/uniir_blip/backbone/configs/bert_config.json
uniir_for_pyserini/models/uniir_blip/backbone/configs/med_config.json
uniir_for_pyserini/models/uniir_blip/backbone/transform/__init__.py
uniir_for_pyserini/models/uniir_blip/backbone/transform/blip_transform.py
uniir_for_pyserini-0.1.1.dist-info/licenses/LICENSE
uniir_for_pyserini-0.1.1.dist-info/METADATA
uniir_for_pyserini-0.1.1.dist-info/WHEEL
uniir_for_pyserini-0.1.1.dist-info/top_level.txt
uniir_for_pyserini-0.1.1.dist-info/RECORD
