Metadata-Version: 2.4
Name: uniir_for_pyserini
Version: 0.1.1
Summary: Fork of the original UniIR repository modified for easy and simple Pyserini integration
Author-email: Cong Wei <lim142857@gmail.com>, Wenhu Chen <wenhuchen@uwaterloo.ca>, Sahel Sharifymoghaddam <sahel.sharifymoghaddam@uwaterloo.ca>, Zibo Guo <daniel168.guo@gmail.com>
Project-URL: Homepage, https://github.com/castorini/UniIR-for-Pyserini
Project-URL: Bug Tracker, https://github.com/castorini/UniIR-for-Pyserini/issues
Classifier: Programming Language :: Python :: 3
Classifier: License :: OSI Approved :: Apache Software License
Classifier: Operating System :: OS Independent
Requires-Python: >=3.10
License-File: LICENSE
Requires-Dist: tqdm
Requires-Dist: pyyaml
Requires-Dist: omegaconf
Requires-Dist: ftfy
Requires-Dist: regex
Requires-Dist: typeguard
Requires-Dist: timm
Requires-Dist: huggingface-hub
Requires-Dist: pandas>=1.4.0
Requires-Dist: pillow>=10.2.0
Requires-Dist: torch>=2.4.0
Requires-Dist: torchvision>=0.15.0
Requires-Dist: numpy>=1.18.1
Requires-Dist: transformers>=4.6.0
Requires-Dist: fairscale>=0.4.0
Requires-Dist: opencv-python>=4.5.0
Dynamic: license-file
